amusing/__init__.py
amusing/printing.py
amusing/munim/__init__.py
amusing/munim/audiomanip.py
amusing/munim/colormaps.py
amusing/munim/munim.py
amusing/munim/oscilloscope.py
amusing/munim/spectogram.py
amusing/score/__init__.py
amusing/score/animate.py
amusing/score/mscx.py
amusing-0.1.1.dist-info/LICENCE
amusing-0.1.1.dist-info/METADATA
amusing-0.1.1.dist-info/WHEEL
amusing-0.1.1.dist-info/top_level.txt
amusing-0.1.1.dist-info/RECORD
