Metadata-Version: 2.1
Name: amusing
Version: 0.1.1
Summary: animated sheet music using MuseScore
Home-page: https://github.com/leftgoes/aMusing
Author: leftgoes (Ha Jong Kim)
Author-email: yluminance@gmail.com
Classifier: Programming Language :: Python :: 3
Classifier: License :: OSI Approved :: MIT License
Classifier: Operating System :: OS Independent
Requires-Python: >=3.7
License-File: LICENCE
Requires-Dist: audio2numpy
Requires-Dist: numpy
Requires-Dist: opencv-python
Requires-Dist: scipy
